feyngraph-0.1.0b4.data/data/share/FeynGraph/feyngraph.m
feyngraph-0.1.0b4.data/data/share/FeynGraph/feyngraph.tikzdefs
feyngraph-0.1.0b4.data/data/share/FeynGraph/feyngraph.tikzstyles
feyngraph-0.1.0b4.data/data/share/FeynGraph/templates/empty.jinja
feyngraph-0.1.0b4.data/data/share/FeynGraph/templates/json.jinja
feyngraph-0.1.0b4.data/scripts/feyngraph
feyngraph-0.1.0b4.dist-info/METADATA
feyngraph-0.1.0b4.dist-info/WHEEL
feyngraph-0.1.0b4.dist-info/licenses/LICENSE
feyngraph/__init__.py
feyngraph/feyngraph.abi3.so
feyngraph/feyngraph.pyi
feyngraph/py.typed
feyngraph/topology.py
feyngraph/topology.pyi
feyngraph/wolfram.py
feyngraph-0.1.0b4.dist-info/RECORD
