Metadata-Version: 2.4
Name: feyngraph
Version: 0.1.0b4
Classifier: Development Status :: 4 - Beta
Classifier: Environment :: Console
Classifier: Intended Audience :: Science/Research
Classifier: Programming Language :: Rust
Classifier: Programming Language :: Python
Classifier: Programming Language :: Python :: 3.10
Classifier: Programming Language :: Python :: 3.11
Classifier: Programming Language :: Python :: 3.12
Classifier: Programming Language :: Python :: 3.13
Classifier: Programming Language :: Python :: Implementation :: CPython
Classifier: Topic :: Scientific/Engineering :: Physics
Requires-Dist: rich>=14.1.0,<15.0.0 ; extra == 'cli'
Requires-Dist: rich-argparse>=1.7.1,<2.0.0 ; extra == 'cli'
Requires-Dist: tomli>=2.2.1,<3.0.0 ; python_full_version < '3.11' and extra == 'cli'
Requires-Dist: jinja2>=3.1.6,<4.0.0 ; extra == 'cli'
Provides-Extra: cli
License-File: LICENSE
Summary: A modern Feynman diagram generator
Author: Jens Braun <j.braun@kit.edu>
Author-email: Jens Braun <j.braun@kit.edu>
License: MPL-2.0
Requires-Python: >=3.10
Project-URL: Repository, https://github.com/jens-braun/feyngraph
Project-URL: Documentation, https://jens-braun.github.io/FeynGraph/
